subbud/__init__.py
subbud/main.py
subbud-0.0.2.dist-info/METADATA
subbud-0.0.2.dist-info/WHEEL
subbud-0.0.2.dist-info/entry_points.txt
subbud-0.0.2.dist-info/top_level.txt
subbud-0.0.2.dist-info/RECORD
