Metadata-Version: 2.1
Name: subbud
Version: 0.0.2
Summary: A short description of the package
Home-page: https://github.com/4riful/subbud
Author: Your Name
Author-email: your.email@example.com
Project-URL: Bug Tracker, https://github.com/4riful/subbud/issues
Classifier: Programming Language :: Python :: 3
Classifier: License :: OSI Approved :: MIT License
Classifier: Operating System :: OS Independent
Requires-Python: >=3.6
